models/__init__.py
models/agent_endpoint.py
models/agent_endpoint_py3.py
models/attribute_filter.py
models/attribute_filter_py3.py
models/attribute_value.py
models/attribute_value_py3.py
models/basic_message_contract.py
models/basic_message_contract_py3.py
models/basic_message_parameters.py
models/basic_message_parameters_py3.py
models/basic_message_record.py
models/basic_message_record_py3.py
models/connection_contract.py
models/connection_contract_py3.py
models/connection_invitation_parameters.py
models/connection_invitation_parameters_py3.py
models/credential_contract.py
models/credential_contract_py3.py
models/credential_definition_contract.py
models/credential_definition_contract_py3.py
models/credential_definition_from_schema_parameters.py
models/credential_definition_from_schema_parameters_py3.py
models/credential_definition_parameters.py
models/credential_definition_parameters_py3.py
models/credential_offer_parameters.py
models/credential_offer_parameters_py3.py
models/issuer_status_contract.py
models/issuer_status_contract_py3.py
models/network_contract.py
models/network_contract_py3.py
models/network_txn_agreement_contract.py
models/network_txn_agreement_contract_py3.py
models/proof_attribute_contract.py
models/proof_attribute_contract_py3.py
models/proof_attribute_info.py
models/proof_attribute_info_py3.py
models/proof_predicate_info.py
models/proof_predicate_info_py3.py
models/proof_request.py
models/proof_request_py3.py
models/revocation_interval.py
models/revocation_interval_py3.py
models/schema_parameters.py
models/schema_parameters_py3.py
models/schema_record.py
models/schema_record_py3.py
models/tenant_contract.py
models/tenant_contract_py3.py
models/tenant_extended_information_contract.py
models/tenant_extended_information_contract_py3.py
models/tenant_parameters.py
models/tenant_parameters_py3.py
models/verification_contract.py
models/verification_contract_py3.py
streetcred_id_service_clients-1.0.dist-info/DESCRIPTION.rst
streetcred_id_service_clients-1.0.dist-info/METADATA
streetcred_id_service_clients-1.0.dist-info/RECORD
streetcred_id_service_clients-1.0.dist-info/WHEEL
streetcred_id_service_clients-1.0.dist-info/metadata.json
streetcred_id_service_clients-1.0.dist-info/top_level.txt
