Metadata-Version: 2.0
Name: streetcred-id-service-clients
Version: 1.0
Summary: Service Clients for our Agency and Custodian API
Home-page: https://github.com/streetcred-id/
Author: Streetcred ID
Author-email: michael.black@streetcred.id
License: UNKNOWN
Platform: UNKNOWN
Classifier: Programming Language :: Python :: 3
Classifier: License :: OSI Approved :: Apache Software License
Classifier: Operating System :: OS Independent
Requires-Python: >=3.6
